igsupload/__init__.py
igsupload/config.py
igsupload/document_reference.py
igsupload/extract_csv.py
igsupload/finish_upload.py
igsupload/get_presigned_url.py
igsupload/get_token.py
igsupload/igs_notification.py
igsupload/igsupload_logger.py
igsupload/long_polling_val.py
igsupload/main.py
igsupload/post_document_reference.py
igsupload/sha256_hash.py
igsupload/start_validation.py
igsupload/upload_chunks.py
igsupload/workflow.py
igsupload-1.0.1.dist-info/licenses/LICENSE
igsupload-1.0.1.dist-info/METADATA
igsupload-1.0.1.dist-info/WHEEL
igsupload-1.0.1.dist-info/entry_points.txt
igsupload-1.0.1.dist-info/top_level.txt
igsupload-1.0.1.dist-info/RECORD
