Metadata-Version: 2.4
Name: igsupload
Version: 1.0.1
Summary: Automated upload of sequencing data (FASTQ/FASTQ.GZIP) to the DEMIS portal (RKI) for the IGS.
Requires-Python: >=3.13
License-File: LICENSE
Requires-Dist: typer>=0.16
Requires-Dist: requests>=2.32.4
Requires-Dist: python-dotenv>=1.1.1
Provides-Extra: dev
Requires-Dist: pytest>=8; extra == "dev"
Requires-Dist: pytest-cov>=5; extra == "dev"
Requires-Dist: pytest-mock>=3.14.1; extra == "dev"
Dynamic: description
Dynamic: description-content-type
Dynamic: license-file
Dynamic: provides-extra
Dynamic: requires-dist
Dynamic: requires-python
Dynamic: summary
